<?xml version="1.0" encoding="UTF-8" ?>
<phpdoc>
	<title><![CDATA[Jomres Core]]></title>
	<parser>
		<target>data/output</target>
		<markers>
			<item>TODO</item>
			<item>FIXME</item>
		</markers>
		<extensions>
			<extension>php</extension>
		</extensions>
	</parser>
	<transformations>
		<template name="responsive-twig" />
	</transformations>
	<transformer>
		<target>data/output</target>
	</transformer>
	<files>
		<directory>C:\wamp64\www\joomla_portal\jomres</directory>
		<ignore>core-plugins\</ignore>
		<ignore>libraries\node_modules</ignore>
		<ignore>\libraries\vendor\</ignore>
		<ignore>remote_plugins\</ignore>
		<ignore>sessions\</ignore>
		<ignore>temp\</ignore>
		<ignore>updates\</ignore>
		<ignore>uploadedimages\</ignore>
		<ignore>assets\</ignore>
		<ignore>configuration.php</ignore>
		<ignore>encryption_key.class.php</ignore>
	</files>
</phpdoc>